figshare_get/__init__.py
figshare_get/__main__.py
figshare_get/_version.py
figshare_get/cli.py
figshare_get-0.1.0.dist-info/METADATA
figshare_get-0.1.0.dist-info/WHEEL
figshare_get-0.1.0.dist-info/entry_points.txt
figshare_get-0.1.0.dist-info/licenses/LICENSE
figshare_get-0.1.0.dist-info/RECORD
